camden_registration_api/__init__.py
camden_registration_api/camden_api_client.py
camden_registration_api-1.1.1.dist-info/LICENSE
camden_registration_api-1.1.1.dist-info/METADATA
camden_registration_api-1.1.1.dist-info/WHEEL
camden_registration_api-1.1.1.dist-info/RECORD
