Metadata-Version: 2.1
Name: camden-registration-api
Version: 1.1.1
Summary: client for interracting with camden website using api
Home-page: https://github.com/polovinko1980/camden-registration-api
License: MIT
Author: Alex Polovinko
Author-email: alex.polovinko@gmail.com
Maintainer: Alex Polovinko
Maintainer-email: alex.polovinko@gmail.com
Requires-Python: >=3.9,<4.0
Classifier: License :: OSI Approved :: MIT License
Classifier: Programming Language :: Python :: 3
Classifier: Programming Language :: Python :: 3.9
Classifier: Programming Language :: Python :: 3.10
Classifier: Programming Language :: Python :: 3.11
Classifier: Programming Language :: Python :: 3.12
Requires-Dist: PyYAML (>=6.0,<7.0)
Requires-Dist: pytz (>=2024.2,<2025.0)
Requires-Dist: requests (>=2.32.3,<3.0.0)
Project-URL: Repository, https://github.com/polovinko1980/camden-registration-api
